{
	"configurations" : 
	[
		{
			"directories" : 
			[
				{
					"build" : ".",
					"hasInstallRule" : true,
					"jsonFile" : "directory-.-764b60b4474842d2318f.json",
					"minimumCMakeVersion" : 
					{
						"string" : "3.12"
					},
					"projectIndex" : 0,
					"source" : ".",
					"targetIndexes" : 
					[
						0,
						1,
						2,
						3,
						4,
						5,
						6,
						7,
						8,
						9,
						10,
						11,
						12,
						13,
						14,
						15
					]
				}
			],
			"name" : "",
			"projects" : 
			[
				{
					"directoryIndexes" : 
					[
						0
					],
					"name" : "bumperbot_cpp_examples",
					"targetIndexes" : 
					[
						0,
						1,
						2,
						3,
						4,
						5,
						6,
						7,
						8,
						9,
						10,
						11,
						12,
						13,
						14,
						15
					]
				}
			],
			"targets" : 
			[
				{
					"directoryIndex" : 0,
					"id" : "bumperbot_cpp_examples_uninstall::@6890427a1f51a3e7e1df",
					"jsonFile" : "target-bumperbot_cpp_examples_uninstall-71ae1b913415ab1e03fc.json",
					"name" : "bumperbot_cpp_examples_uninstall",
					"projectIndex" : 0
				},
				{
					"directoryIndex" : 0,
					"id" : "simple_action_client::@6890427a1f51a3e7e1df",
					"jsonFile" : "target-simple_action_client-e149d9b0204212b048c6.json",
					"name" : "simple_action_client",
					"projectIndex" : 0
				},
				{
					"directoryIndex" : 0,
					"id" : "simple_action_client_node::@6890427a1f51a3e7e1df",
					"jsonFile" : "target-simple_action_client_node-d9c6c25d48c1581f6cb8.json",
					"name" : "simple_action_client_node",
					"projectIndex" : 0
				},
				{
					"directoryIndex" : 0,
					"id" : "simple_action_server::@6890427a1f51a3e7e1df",
					"jsonFile" : "target-simple_action_server-eb3945ffee1b998218cb.json",
					"name" : "simple_action_server",
					"projectIndex" : 0
				},
				{
					"directoryIndex" : 0,
					"id" : "simple_action_server_node::@6890427a1f51a3e7e1df",
					"jsonFile" : "target-simple_action_server_node-b587c5d13dbd73b05e6f.json",
					"name" : "simple_action_server_node",
					"projectIndex" : 0
				},
				{
					"directoryIndex" : 0,
					"id" : "simple_lifecycle_node::@6890427a1f51a3e7e1df",
					"jsonFile" : "target-simple_lifecycle_node-deb633bb17e1ae308f40.json",
					"name" : "simple_lifecycle_node",
					"projectIndex" : 0
				},
				{
					"directoryIndex" : 0,
					"id" : "simple_parameter::@6890427a1f51a3e7e1df",
					"jsonFile" : "target-simple_parameter-aaee4e69bf78bfd3f6b7.json",
					"name" : "simple_parameter",
					"projectIndex" : 0
				},
				{
					"directoryIndex" : 0,
					"id" : "simple_publisher::@6890427a1f51a3e7e1df",
					"jsonFile" : "target-simple_publisher-00c86a8d4029de204fdd.json",
					"name" : "simple_publisher",
					"projectIndex" : 0
				},
				{
					"directoryIndex" : 0,
					"id" : "simple_qos_publisher::@6890427a1f51a3e7e1df",
					"jsonFile" : "target-simple_qos_publisher-4daa4f364ef7de08fc63.json",
					"name" : "simple_qos_publisher",
					"projectIndex" : 0
				},
				{
					"directoryIndex" : 0,
					"id" : "simple_qos_subscriber::@6890427a1f51a3e7e1df",
					"jsonFile" : "target-simple_qos_subscriber-80a192e8f7fa558b30ff.json",
					"name" : "simple_qos_subscriber",
					"projectIndex" : 0
				},
				{
					"directoryIndex" : 0,
					"id" : "simple_service_client::@6890427a1f51a3e7e1df",
					"jsonFile" : "target-simple_service_client-23cfd6403552ab6e0997.json",
					"name" : "simple_service_client",
					"projectIndex" : 0
				},
				{
					"directoryIndex" : 0,
					"id" : "simple_service_server::@6890427a1f51a3e7e1df",
					"jsonFile" : "target-simple_service_server-6659d897277326e0a5da.json",
					"name" : "simple_service_server",
					"projectIndex" : 0
				},
				{
					"directoryIndex" : 0,
					"id" : "simple_subscriber::@6890427a1f51a3e7e1df",
					"jsonFile" : "target-simple_subscriber-42c6852c986852860c62.json",
					"name" : "simple_subscriber",
					"projectIndex" : 0
				},
				{
					"directoryIndex" : 0,
					"id" : "simple_tf_kinematics::@6890427a1f51a3e7e1df",
					"jsonFile" : "target-simple_tf_kinematics-dfbb3251714042f548a0.json",
					"name" : "simple_tf_kinematics",
					"projectIndex" : 0
				},
				{
					"directoryIndex" : 0,
					"id" : "simple_turtlesim_kinematics::@6890427a1f51a3e7e1df",
					"jsonFile" : "target-simple_turtlesim_kinematics-1ab9c464e918752898ec.json",
					"name" : "simple_turtlesim_kinematics",
					"projectIndex" : 0
				},
				{
					"directoryIndex" : 0,
					"id" : "uninstall::@6890427a1f51a3e7e1df",
					"jsonFile" : "target-uninstall-31b9ebf77f4a677b7f30.json",
					"name" : "uninstall",
					"projectIndex" : 0
				}
			]
		}
	],
	"kind" : "codemodel",
	"paths" : 
	{
		"build" : "/home/nikhilsai/bumperbot_ws/build/bumperbot_cpp_examples",
		"source" : "/home/nikhilsai/bumperbot_ws/src/bumperbot_cpp_examples"
	},
	"version" : 
	{
		"major" : 2,
		"minor" : 3
	}
}
